exclog/__init__.py
exclog/exclog.py
exclog/test.py
exclog-0.0.1.dist-info/METADATA
exclog-0.0.1.dist-info/WHEEL
exclog-0.0.1.dist-info/top_level.txt
exclog-0.0.1.dist-info/RECORD
