Metadata-Version: 2.1
Name: exclog
Version: 0.0.1
Summary: Easy python exception logging tool
Home-page: https://github.com/mtvy/exclog.git
Author: Matvei Prudnikov
Author-email: m.d.prudnik@gmail.com
License: MIT
